{
  "extends": "./base.json",
  "compilerOptions": {
    "lib": ["DOM", "DOM.Iterable", "ES2022"],
    "jsx": "react-jsx",
    "allowJs": true,
    "skipLibCheck": true,
    "esModuleInterop": true,
    "allowSyntheticDefaultImports": true,
    "forceConsistentCasingInFileNames": true,
    "moduleResolution": "bundler",
    "resolveJsonModule": true,
    "isolatedModules": true,
    "noEmit": true,
    "incremental": true,
    "plugins": [
      {
        "name": "next"
      }
    ],
    "paths": {
      "@/*": ["./src/*"]
    }
  },
  "include": [
    "next-env.d.ts",
    "**/*.ts",
    "**/*.tsx",
    ".next/types/**/*.ts"
  ]
}
